{
    "HEAD_S1": {
        "id": "HEAD_S1",
        "origin": "AREA_1",
        "part": "HEAD",
        "set": "SET_1",
        "name": "Adventurer Cap",
        "description": "It's dangerous to go alone! Wear this and stay safe!",
        "sprites": {
            "one-star": "#TODO",
            "three-star": "#TODO",
            "five-star": "#TODO"
        },
        "stats": [
            {
                "hit_point": 40,
                "attack": 0,
                "physical_damage": 0,
                "ranged_physical_damage": 0,
                "magic_damage": 0,
                "dodge_rate": 0,
                "critical_rate": 0,
                "critical_damage": 0,
                "physical_damage_reduction": 0,
                "magic_damage_reduction": 0,
                "healing_bonus": 0
            },
            {
                "hit_point": 45,
                "attack": 0,
                "physical_damage": 0,
                "ranged_physical_damage": 0,
                "magic_damage": 0,
                "dodge_rate": 0,
                "critical_rate": 0,
                "critical_damage": 0,
                "physical_damage_reduction": 0,
                "magic_damage_reduction": 0,
                "healing_bonus": 0
            },
            {
                "hit_point": 50,
                "attack": 0,
                "physical_damage": 0,
                "ranged_physical_damage": 0,
                "magic_damage": 0,
                "dodge_rate": 0,
                "critical_rate": 0,
                "critical_damage": 0,
                "physical_damage_reduction": 0,
                "magic_damage_reduction": 0,
                "healing_bonus": 0
            },
            {
                "hit_point": 55,
                "attack": 0,
                "physical_damage": 0,
                "ranged_physical_damage": 0,
                "magic_damage": 0,
                "dodge_rate": 0,
                "critical_rate": 0,
                "critical_damage": 0,
                "physical_damage_reduction": 0,
                "magic_damage_reduction": 0,
                "healing_bonus": 0
            },
            {
                "hit_point": 60,
                "attack": 0,
                "physical_damage": 0,
                "ranged_physical_damage": 0,
                "magic_damage": 0,
                "dodge_rate": 0,
                "critical_rate": 0,
                "critical_damage": 0,
                "physical_damage_reduction": 0,
                "magic_damage_reduction": 0,
                "healing_bonus": 0
            }
        ],
        "bonus": {
            "HP": 0,
            "Atk": 0,
            "PD": 0,
            "RPD": 3,
            "MD": 0,
            "DR": 0,
            "CR": 0,
            "CD": 0,
            "PDR": 0,
            "MDR": 0,
            "HB": 0,
            "%": false
        }
    }
}